mailpeek/__init__.py
mailpeek/cli.py
mailpeek/imap_idle_listener.py
mailpeek/reader.py
mailpeek-0.1.0.dist-info/METADATA
mailpeek-0.1.0.dist-info/WHEEL
mailpeek-0.1.0.dist-info/entry_points.txt
mailpeek-0.1.0.dist-info/RECORD
