Metadata-Version: 2.3
Name: mailpeek
Version: 0.1.0
Summary: A lightweight IMAP-based email reader for Python/Django
License: MIT
Keywords: email,imap,inbox,django,cli,attachment,idle
Author: Anand R Nair
Author-email: anand547@outlook.com
Requires-Python: >=3.9
Classifier: License :: OSI Approved :: MIT License
Classifier: Programming Language :: Python :: 3
Classifier: Programming Language :: Python :: 3.9
Classifier: Programming Language :: Python :: 3.10
Classifier: Programming Language :: Python :: 3.11
Classifier: Programming Language :: Python :: 3.12
Classifier: Programming Language :: Python :: 3.13
Requires-Dist: imapclient (>=3.0.1)
Requires-Dist: pyzmail36 (>=1.0.5)
Project-URL: Homepage, https://github.com/anandrnair547/mailpeek
Project-URL: Repository, https://github.com/anandrnair547/mailpeek
